{
  "default": {
    "nil-cmake": {
      "baseline": "0.0.3",
      "port-version": 0
    },
    "nil-xalt": {
      "baseline": "1.4.2",
      "port-version": 0
    },
    "nil-clix": {
      "baseline": "1.0.9",
      "port-version": 0
    },
    "nil-gate": {
      "baseline": "1.6.6",
      "port-version": 0
    },
    "nil-service": {
      "baseline": "1.0.16",
      "port-version": 0
    },
    "nil-xit": {
      "baseline": "0.3.10",
      "port-version": 0
    },
    "nil-xit-test": {
      "baseline": "0.0.18",
      "port-version": 0
    }
  }
}
